HISTORY.txt
LICENSE.txt
MANIFEST.in
README.md
setup.cfg
setup.py
sparc/__init__.py
sparc.common.egg-info/PKG-INFO
sparc.common.egg-info/SOURCES.txt
sparc.common.egg-info/dependency_links.txt
sparc.common.egg-info/entry_points.txt
sparc.common.egg-info/namespace_packages.txt
sparc.common.egg-info/not-zip-safe
sparc.common.egg-info/requires.txt
sparc.common.egg-info/top_level.txt
sparc/common/__init__.py
sparc/common/cli.py
sparc/common/configure.py
sparc/common/configure.zcml
sparc/common/interfaces.py
sparc/common/log.py
sparc/common/tests/__init__.py
sparc/common/tests/test_cli.py